{"topics":[{"topicLabel":"Similar and the same","topicThesaurusName":"topics","topicUrl":"http://dictionary.cambridge.org/topics/comparing-and-classifying/similar-and-the-same/","topicId":"similar-and-the-same","topicParentId":"comparing-and-classifying"}],"dictionaryCode":"american-english","entryContent":"<di><header><title>level<\/title><\/header> <pos-block><header><info><posgram><pos>adjective<\/pos><\/posgram> <audio type=\"pronunciation\" region=\"us\"><source type=\"audio/mpeg\" src=\"https://dictionary.cambridge.org/media/american-english/us_pron/l/lev/level/level.mp3\"/><source type=\"audio/ogg\" src=\"https://dictionary.cambridge.org/media/american-english/us_pron_ogg/l/lev/level/level.ogg\"/><\/audio> <pron>/<ipa>ˈlev·əl<\/ipa>/<\/pron> <\/info><\/header><sense-block><header><title>HORIZONTAL<\/title><\/header> <def-block><definition><info><lvl>\u203a<\/lvl> <\/info><def>(of a surface) not rising or falling or higher on one side, but even in all directions; horizontal or flat: <\/def><\/definition><examp><eg>The table wobbles because the floor is not level.<\/eg><\/examp><\/def-block> <def-block><definition><info><lvl>\u203a<\/lvl> <\/info><def>Something that is level with something else is at the same height: <\/def><\/definition><examp><eg>The top of the tree is level with his bedroom window.<\/eg><\/examp><\/def-block> <def-block><definition><info><lvl>\u203a<\/lvl> <\/info><def>A level spoon or cup is filled with something just to the top edge.<\/def><\/definition><\/def-block> <def-block><definition><info><lvl>\u203a<\/lvl> <\/info><def>If you speak in a level voice, you speak in a calm and controlled way.<\/def><\/definition><\/def-block><\/sense-block> <entry-xref>→ <lab>Idioms<\/lab> <x dictionary=\"american-english\" entryId=\"a-level-playing-field\"><f>a level playing field<\/f><\/x>, <x dictionary=\"american-english\" entryId=\"on-the-level\"><f>on the level<\/f><\/x><\/entry-xref><\/pos-block> <pos-block><header><info><posgram><pos>noun<\/pos><\/posgram> <audio type=\"pronunciation\" region=\"us\"><source type=\"audio/mpeg\" src=\"https://dictionary.cambridge.org/media/american-english/us_pron/l/lev/level/level.mp3\"/><source type=\"audio/ogg\" src=\"https://dictionary.cambridge.org/media/american-english/us_pron_ogg/l/lev/level/level.ogg\"/><\/audio> <pron>/<ipa>ˈlev·əl<\/ipa>/<\/pron> <\/info><\/header><sense-block><header><title>POSITION<\/title><\/header> <def-block><definition><info><lvl>\u203a<\/lvl> <gram>[<gcs><gc>C/U<\/gc><\/gcs>]<\/gram><\/info> <def>a particular position, degree, or amount of something, esp. compared with other possible positions, degrees, or amounts: <\/def><\/definition><examp><info><gram>[<gcs><gc>C<\/gc><\/gcs>]<\/gram><\/info><eg>The water level in the lake is higher after a heavy rain.<\/eg><\/examp><examp><info><gram>[<gcs><gc>U<\/gc><\/gcs>]<\/gram><\/info><eg>The big debate is whether more decisions should be made at the local level or at the national level.<\/eg><\/examp><examp><info><gram>[<gcs><gc>C<\/gc><\/gcs>]<\/gram><\/info><eg>He achieved a high level of skill as an interpreter.<\/eg><\/examp><examp><info><gram>[<gcs><gc>U<\/gc><\/gcs>]<\/gram><\/info><eg>We publish a dictionary for intermediate level students.<\/eg><\/examp><\/def-block> <def-block><definition><info><lvl>\u203a<\/lvl> <gram>[<gcs><gc>C/U<\/gc><\/gcs>]<\/gram><\/info> <def>A level is also one of several floors at different heights in a building: <\/def><\/definition><examp><info><gram>[<gcs><gc>C<\/gc><\/gcs>]<\/gram><\/info><eg>The reception area is on the ground level.<\/eg><\/examp><\/def-block><\/sense-block> <sense-block><header><title>HORIZONTAL<\/title><\/header> <def-block><definition><info><lvl>\u203a<\/lvl> <gram>[<gcs><gc>C<\/gc><\/gcs>]<\/gram><\/info> <def>a tool containing a tube of liquid with an air bubble in it, which shows whether a surface is horizontal by the position of the bubble<\/def><\/definition><\/def-block><\/sense-block><\/pos-block> <pos-block><header><info><posgram><pos>verb<\/pos> <gram>[<gcs><gc>T<\/gc><\/gcs>]<\/gram><\/posgram> <audio type=\"pronunciation\" region=\"us\"><source type=\"audio/mpeg\" src=\"https://dictionary.cambridge.org/media/american-english/us_pron/l/lev/level/level.mp3\"/><source type=\"audio/ogg\" src=\"https://dictionary.cambridge.org/media/american-english/us_pron_ogg/l/lev/level/level.ogg\"/><\/audio> <pron>/<ipa>ˈlev·əl<\/ipa>/<\/pron> <\/info><\/header><sense-block><header><title>AIM<\/title><\/header> <def-block><definition><info><lvl>\u203a<\/lvl> <\/info><def>to aim or direct something at someone or something: <\/def><\/definition><examp><eg>Soldiers leveled their weapons.<\/eg><\/examp><examp><eg>Criticism of the program was leveled by a number of politicians.<\/eg><\/examp><\/def-block><\/sense-block> <sense-block><header><title>HORIZONTAL<\/title><\/header> <def-block><definition><info><lvl>\u203a<\/lvl> <\/info><def>to make something level: <\/def><\/definition><examp><eg>We had to level the backyard before putting up the pool.<\/eg><\/examp><\/def-block> <def-block><definition><info><lvl>\u203a<\/lvl> <\/info><def>To level buildings or other structures is to destroy them by causing them to fall down: <\/def><\/definition><examp><eg>Her grandfather survived the 1906 earthquake that leveled San Francisco.<\/eg><\/examp><\/def-block><\/sense-block> <entry-xref>→ <lab>Phrasal verbs<\/lab> <x dictionary=\"american-english\" entryId=\"level-off\"><f>level off<\/f><\/x>, <x dictionary=\"american-english\" entryId=\"level-with-someone\"><f>level with <i>someone<\/i><\/f><\/x><\/entry-xref><\/pos-block><footer><copyright>(Definition of level  from the <x href=\"https://dictionary.cambridge.org/dictionary/american-english/\" title=\"Cambridge Academic Content Dictionary\n\">Cambridge Academic Content Dictionary\n<\/x> © Cambridge University Press)<\/copyright><\/footer><\/di>\n","entryLabel":"level","entryUrl":"http://dictionary.cambridge.org/dictionary/american-english/level","format":"xml","entryId":"level"}